nikas/__init__.py
nikas/config.py
nikas/core.py
nikas/dispatch.py
nikas/migrate.py
nikas/nikas.cfg
nikas/run.py
nikas/wsgi.py
nikas/css/nikas-admin.css
nikas/css/nikas-admin.css.map
nikas/css/nikas-dark.css
nikas/css/nikas-dark.css.map
nikas/css/nikas-light.css
nikas/css/nikas-light.css.map
nikas/db/__init__.py
nikas/db/comments.py
nikas/db/preferences.py
nikas/db/spam.py
nikas/db/threads.py
nikas/ext/__init__.py
nikas/ext/notifications.py
nikas/img/favicon.ico
nikas/img/logo.png
nikas/js/admin.js
nikas/js/count.dev.js
nikas/js/count.min.js
nikas/js/embed.dev.js
nikas/js/embed.min.js
nikas/templates/admin.html
nikas/templates/disabled.html
nikas/templates/login.html
nikas/utils/__init__.py
nikas/utils/hash.py
nikas/utils/html.py
nikas/utils/http.py
nikas/utils/parse.py
nikas/views/__init__.py
nikas/views/comments.py
nikas-2.1.1.dist-info/LICENSE
nikas-2.1.1.dist-info/METADATA
nikas-2.1.1.dist-info/WHEEL
nikas-2.1.1.dist-info/entry_points.txt
nikas-2.1.1.dist-info/top_level.txt
nikas-2.1.1.dist-info/RECORD
