Metadata-Version: 2.1
Name: nikas
Version: 2.1.1
Summary: The first persian comment system 
Home-page: https://github.com/Nikas-Project/Server
Author: Arash Hatami
Author-email: hatamiarash7@gmail.com
License: MIT
Platform: UNKNOWN
Classifier: Development Status :: 5 - Production/Stable
Classifier: Topic :: Utilities
Classifier: Topic :: Internet
Classifier: Topic :: Internet :: WWW/HTTP :: HTTP Servers
Classifier: Topic :: Internet :: WWW/HTTP :: WSGI :: Application
Classifier: Intended Audience :: Information Technology
Classifier: Intended Audience :: System Administrators
Classifier: Natural Language :: Persian
Classifier: License :: OSI Approved :: MIT License
Classifier: Programming Language :: Python :: 3.7
Classifier: Programming Language :: Python :: 3.8
Classifier: Programming Language :: Python :: 3.9
Classifier: Programming Language :: Python :: 3.10
Requires-Python: >=3.6
Requires-Dist: argon2-cffi (==21.3.0)
Requires-Dist: bleach (==5.0.1)
Requires-Dist: cffi (==1.15.1)
Requires-Dist: Flask (==2.2.2)
Requires-Dist: Flask-Caching (==2.0.1)
Requires-Dist: gevent (==21.12.0)
Requires-Dist: html5lib (==1.1)
Requires-Dist: itsdangerous (==2.1.2)
Requires-Dist: Jinja2 (==3.1.2)
Requires-Dist: MarkupSafe (==2.1.1)
Requires-Dist: misaka (==2.1.1)
Requires-Dist: pytest (==7.1.3)
Requires-Dist: pytest-cov (==3.0.0)
Requires-Dist: Werkzeug (==2.2.2)
